kwnlp_sql_parser/__init__.py
kwnlp_sql_parser/wp_sql_dump.py
kwnlp_sql_parser/wp_sql_patterns.py
kwnlp_sql_parser-0.0.2.dist-info/AUTHORS.md
kwnlp_sql_parser-0.0.2.dist-info/LICENSE
kwnlp_sql_parser-0.0.2.dist-info/METADATA
kwnlp_sql_parser-0.0.2.dist-info/WHEEL
kwnlp_sql_parser-0.0.2.dist-info/top_level.txt
kwnlp_sql_parser-0.0.2.dist-info/RECORD
