Metadata-Version: 2.1
Name: kwnlp-sql-parser
Version: 0.0.2
Summary: Utility for parsing Wikipedia SQL dumps into CSVs.
Home-page: https://github.com/kensho-technologies/kwnlp-sql-parser
Author: Kensho Technologies LLC.
Author-email: kwnlp@kensho.com
License: Apache 2.0
Keywords: wikipedia sql dump open data
Classifier: Development Status :: 4 - Beta
Classifier: Intended Audience :: Developers
Classifier: License :: OSI Approved :: Apache Software License
Classifier: Programming Language :: Python :: 3 :: Only
Classifier: Programming Language :: Python :: 3
Classifier: Programming Language :: Python :: 3.6
Classifier: Programming Language :: Python :: 3.7
Classifier: Programming Language :: Python :: 3.8
Requires-Python: >=3.6
License-File: LICENSE
License-File: AUTHORS.md
Provides-Extra: dev
Requires-Dist: pre-commit ; extra == 'dev'
